xaal/__init__.py
xaal/lmsensors/__init__.py
xaal/lmsensors/__main__.py
xaal/lmsensors/lmsensors.py
xaal_lmsensors-0.1.2.dist-info/METADATA
xaal_lmsensors-0.1.2.dist-info/WHEEL
xaal_lmsensors-0.1.2.dist-info/top_level.txt
xaal_lmsensors-0.1.2.dist-info/RECORD
